Librería/__init__.py
Librería/bay.py
jbnetwork-0.0.3.dist-info/METADATA
jbnetwork-0.0.3.dist-info/WHEEL
jbnetwork-0.0.3.dist-info/top_level.txt
jbnetwork-0.0.3.dist-info/RECORD
